<stg><name>Four_Term_Multiplication</name>


<trans_list>
</trans_list>



<state_list>

<state id="1" st_id="1">

<operation id="2" st_id="1" stage="1" lat="1">
<core>NULL</core>
<MemPortIdVec></MemPortIdVec>
<condition id="-1">
<or_exp><and_exp></and_exp></or_exp>
</condition>

<Node id="5" bw="8" op_0_bw="8" op_1_bw="8">
<![CDATA[
:0 %p_read37 = read i8 @_ssdm_op_Read.ap_auto.i8, i8 %p_read3

]]></Node>
<StgValue><ssdm name="p_read37"/></StgValue>
</operation>

<operation id="3" st_id="1" stage="1" lat="1">
<core>NULL</core>
<MemPortIdVec></MemPortIdVec>
<condition id="-1">
<or_exp><and_exp></and_exp></or_exp>
</condition>

<Node id="6" bw="8" op_0_bw="8" op_1_bw="8">
<![CDATA[
:1 %p_read26 = read i8 @_ssdm_op_Read.ap_auto.i8, i8 %p_read2

]]></Node>
<StgValue><ssdm name="p_read26"/></StgValue>
</operation>

<operation id="4" st_id="1" stage="1" lat="1">
<core>NULL</core>
<MemPortIdVec></MemPortIdVec>
<condition id="-1">
<or_exp><and_exp></and_exp></or_exp>
</condition>

<Node id="7" bw="8" op_0_bw="8" op_1_bw="8">
<![CDATA[
:2 %p_read15 = read i8 @_ssdm_op_Read.ap_auto.i8, i8 %p_read1

]]></Node>
<StgValue><ssdm name="p_read15"/></StgValue>
</operation>

<operation id="5" st_id="1" stage="1" lat="1">
<core>NULL</core>
<MemPortIdVec></MemPortIdVec>
<condition id="-1">
<or_exp><and_exp></and_exp></or_exp>
</condition>

<Node id="8" bw="8" op_0_bw="8" op_1_bw="8">
<![CDATA[
:3 %p_read_193 = read i8 @_ssdm_op_Read.ap_auto.i8, i8 %p_read

]]></Node>
<StgValue><ssdm name="p_read_193"/></StgValue>
</operation>

<operation id="6" st_id="1" stage="1" lat="1">
<core>NULL</core>
<MemPortIdVec></MemPortIdVec>
<condition id="-1">
<or_exp><and_exp></and_exp></or_exp>
</condition>

<Node id="9" bw="8" op_0_bw="8" op_1_bw="8">
<![CDATA[
:4 %result = shl i8 %p_read_193, i8 1

]]></Node>
<StgValue><ssdm name="result"/></StgValue>
</operation>

<operation id="7" st_id="1" stage="1" lat="1">
<core>NULL</core>
<MemPortIdVec></MemPortIdVec>
<condition id="-1">
<or_exp><and_exp></and_exp></or_exp>
</condition>

<Node id="10" bw="1" op_0_bw="1" op_1_bw="8" op_2_bw="32">
<![CDATA[
:5 %tmp = bitselect i1 @_ssdm_op_BitSelect.i1.i8.i32, i8 %p_read_193, i32 7

]]></Node>
<StgValue><ssdm name="tmp"/></StgValue>
</operation>

<operation id="8" st_id="1" stage="1" lat="1">
<core>LogicGate</core>
<MemPortIdVec></MemPortIdVec>
<condition id="-1">
<or_exp><and_exp><literal name="tmp" val="1"/>
</and_exp></or_exp>
</condition>

<Node id="11" bw="8" op_0_bw="8" op_1_bw="8">
<![CDATA[
:6 %result_1 = xor i8 %result, i8 27

]]></Node>
<StgValue><ssdm name="result_1"/></StgValue>
</operation>

<operation id="9" st_id="1" stage="1" lat="1">
<core>Sel</core>
<MemPortIdVec></MemPortIdVec>
<condition id="-1">
<or_exp><and_exp></and_exp></or_exp>
</condition>

<Node id="12" bw="8" op_0_bw="1" op_1_bw="8" op_2_bw="8">
<![CDATA[
:7 %result_2 = select i1 %tmp, i8 %result_1, i8 %result

]]></Node>
<StgValue><ssdm name="result_2"/></StgValue>
</operation>

<operation id="10" st_id="1" stage="1" lat="1">
<core>NULL</core>
<MemPortIdVec></MemPortIdVec>
<condition id="-1">
<or_exp><and_exp></and_exp></or_exp>
</condition>

<Node id="13" bw="8" op_0_bw="8" op_1_bw="8">
<![CDATA[
:8 %result_3 = shl i8 %p_read15, i8 1

]]></Node>
<StgValue><ssdm name="result_3"/></StgValue>
</operation>

<operation id="11" st_id="1" stage="1" lat="1">
<core>NULL</core>
<MemPortIdVec></MemPortIdVec>
<condition id="-1">
<or_exp><and_exp></and_exp></or_exp>
</condition>

<Node id="14" bw="1" op_0_bw="1" op_1_bw="8" op_2_bw="32">
<![CDATA[
:9 %tmp_1 = bitselect i1 @_ssdm_op_BitSelect.i1.i8.i32, i8 %p_read15, i32 7

]]></Node>
<StgValue><ssdm name="tmp_1"/></StgValue>
</operation>

<operation id="12" st_id="1" stage="1" lat="1">
<core>LogicGate</core>
<MemPortIdVec></MemPortIdVec>
<condition id="-1">
<or_exp><and_exp><literal name="tmp_1" val="1"/>
</and_exp></or_exp>
</condition>

<Node id="15" bw="8" op_0_bw="8" op_1_bw="8">
<![CDATA[
:10 %result_4 = xor i8 %result_3, i8 27

]]></Node>
<StgValue><ssdm name="result_4"/></StgValue>
</operation>

<operation id="13" st_id="1" stage="1" lat="1">
<core>Sel</core>
<MemPortIdVec></MemPortIdVec>
<condition id="-1">
<or_exp><and_exp></and_exp></or_exp>
</condition>

<Node id="16" bw="8" op_0_bw="1" op_1_bw="8" op_2_bw="8">
<![CDATA[
:11 %result_5 = select i1 %tmp_1, i8 %result_4, i8 %result_3

]]></Node>
<StgValue><ssdm name="result_5"/></StgValue>
</operation>

<operation id="14" st_id="1" stage="1" lat="1">
<core>LogicGate</core>
<MemPortIdVec></MemPortIdVec>
<condition id="-1">
<or_exp><and_exp></and_exp></or_exp>
</condition>

<Node id="17" bw="8" op_0_bw="8" op_1_bw="8">
<![CDATA[
:12 %xor_ln15 = xor i8 %result_2, i8 %p_read_193

]]></Node>
<StgValue><ssdm name="xor_ln15"/></StgValue>
</operation>

<operation id="15" st_id="1" stage="1" lat="1">
<core>LogicGate</core>
<MemPortIdVec></MemPortIdVec>
<condition id="-1">
<or_exp><and_exp></and_exp></or_exp>
</condition>

<Node id="18" bw="8" op_0_bw="8" op_1_bw="8">
<![CDATA[
:13 %xor_ln15_1 = xor i8 %result_5, i8 %p_read37

]]></Node>
<StgValue><ssdm name="xor_ln15_1"/></StgValue>
</operation>

<operation id="16" st_id="1" stage="1" lat="1">
<core>LogicGate</core>
<MemPortIdVec></MemPortIdVec>
<condition id="-1">
<or_exp><and_exp></and_exp></or_exp>
</condition>

<Node id="19" bw="8" op_0_bw="8" op_1_bw="8">
<![CDATA[
:14 %xor_ln15_2 = xor i8 %xor_ln15_1, i8 %p_read26

]]></Node>
<StgValue><ssdm name="xor_ln15_2"/></StgValue>
</operation>

<operation id="17" st_id="1" stage="1" lat="1">
<core>LogicGate</core>
<MemPortIdVec></MemPortIdVec>
<condition id="-1">
<or_exp><and_exp></and_exp></or_exp>
</condition>

<Node id="20" bw="8" op_0_bw="8" op_1_bw="8">
<![CDATA[
:15 %xor_ln15_3 = xor i8 %xor_ln15_2, i8 %xor_ln15

]]></Node>
<StgValue><ssdm name="xor_ln15_3"/></StgValue>
</operation>

<operation id="18" st_id="1" stage="1" lat="1">
<core>NULL</core>
<MemPortIdVec></MemPortIdVec>
<condition id="-1">
<or_exp><and_exp></and_exp></or_exp>
</condition>

<Node id="21" bw="8" op_0_bw="8" op_1_bw="8">
<![CDATA[
:16 %result_6 = shl i8 %p_read26, i8 1

]]></Node>
<StgValue><ssdm name="result_6"/></StgValue>
</operation>

<operation id="19" st_id="1" stage="1" lat="1">
<core>NULL</core>
<MemPortIdVec></MemPortIdVec>
<condition id="-1">
<or_exp><and_exp></and_exp></or_exp>
</condition>

<Node id="22" bw="1" op_0_bw="1" op_1_bw="8" op_2_bw="32">
<![CDATA[
:17 %tmp_2 = bitselect i1 @_ssdm_op_BitSelect.i1.i8.i32, i8 %p_read26, i32 7

]]></Node>
<StgValue><ssdm name="tmp_2"/></StgValue>
</operation>

<operation id="20" st_id="1" stage="1" lat="1">
<core>LogicGate</core>
<MemPortIdVec></MemPortIdVec>
<condition id="-1">
<or_exp><and_exp><literal name="tmp_2" val="1"/>
</and_exp></or_exp>
</condition>

<Node id="23" bw="8" op_0_bw="8" op_1_bw="8">
<![CDATA[
:18 %result_7 = xor i8 %result_6, i8 27

]]></Node>
<StgValue><ssdm name="result_7"/></StgValue>
</operation>

<operation id="21" st_id="1" stage="1" lat="1">
<core>Sel</core>
<MemPortIdVec></MemPortIdVec>
<condition id="-1">
<or_exp><and_exp></and_exp></or_exp>
</condition>

<Node id="24" bw="8" op_0_bw="1" op_1_bw="8" op_2_bw="8">
<![CDATA[
:19 %result_8 = select i1 %tmp_2, i8 %result_7, i8 %result_6

]]></Node>
<StgValue><ssdm name="result_8"/></StgValue>
</operation>

<operation id="22" st_id="1" stage="1" lat="1">
<core>LogicGate</core>
<MemPortIdVec></MemPortIdVec>
<condition id="-1">
<or_exp><and_exp></and_exp></or_exp>
</condition>

<Node id="25" bw="8" op_0_bw="8" op_1_bw="8">
<![CDATA[
:20 %xor_ln16 = xor i8 %p_read15, i8 %p_read_193

]]></Node>
<StgValue><ssdm name="xor_ln16"/></StgValue>
</operation>

<operation id="23" st_id="1" stage="1" lat="1">
<core>LogicGate</core>
<MemPortIdVec></MemPortIdVec>
<condition id="-1">
<or_exp><and_exp></and_exp></or_exp>
</condition>

<Node id="26" bw="8" op_0_bw="8" op_1_bw="8">
<![CDATA[
:21 %xor_ln16_1 = xor i8 %result_5, i8 %xor_ln16

]]></Node>
<StgValue><ssdm name="xor_ln16_1"/></StgValue>
</operation>

<operation id="24" st_id="1" stage="1" lat="1">
<core>LogicGate</core>
<MemPortIdVec></MemPortIdVec>
<condition id="-1">
<or_exp><and_exp></and_exp></or_exp>
</condition>

<Node id="27" bw="8" op_0_bw="8" op_1_bw="8">
<![CDATA[
:22 %xor_ln16_2 = xor i8 %result_8, i8 %p_read37

]]></Node>
<StgValue><ssdm name="xor_ln16_2"/></StgValue>
</operation>

<operation id="25" st_id="1" stage="1" lat="1">
<core>LogicGate</core>
<MemPortIdVec></MemPortIdVec>
<condition id="-1">
<or_exp><and_exp></and_exp></or_exp>
</condition>

<Node id="28" bw="8" op_0_bw="8" op_1_bw="8">
<![CDATA[
:23 %xor_ln16_3 = xor i8 %xor_ln16_2, i8 %xor_ln16_1

]]></Node>
<StgValue><ssdm name="xor_ln16_3"/></StgValue>
</operation>

<operation id="26" st_id="1" stage="1" lat="1">
<core>NULL</core>
<MemPortIdVec></MemPortIdVec>
<condition id="-1">
<or_exp><and_exp></and_exp></or_exp>
</condition>

<Node id="29" bw="8" op_0_bw="8" op_1_bw="8">
<![CDATA[
:24 %result_9 = shl i8 %p_read37, i8 1

]]></Node>
<StgValue><ssdm name="result_9"/></StgValue>
</operation>

<operation id="27" st_id="1" stage="1" lat="1">
<core>NULL</core>
<MemPortIdVec></MemPortIdVec>
<condition id="-1">
<or_exp><and_exp></and_exp></or_exp>
</condition>

<Node id="30" bw="1" op_0_bw="1" op_1_bw="8" op_2_bw="32">
<![CDATA[
:25 %tmp_3 = bitselect i1 @_ssdm_op_BitSelect.i1.i8.i32, i8 %p_read37, i32 7

]]></Node>
<StgValue><ssdm name="tmp_3"/></StgValue>
</operation>

<operation id="28" st_id="1" stage="1" lat="1">
<core>LogicGate</core>
<MemPortIdVec></MemPortIdVec>
<condition id="-1">
<or_exp><and_exp><literal name="tmp_3" val="1"/>
</and_exp></or_exp>
</condition>

<Node id="31" bw="8" op_0_bw="8" op_1_bw="8">
<![CDATA[
:26 %result_10 = xor i8 %result_9, i8 27

]]></Node>
<StgValue><ssdm name="result_10"/></StgValue>
</operation>

<operation id="29" st_id="1" stage="1" lat="1">
<core>Sel</core>
<MemPortIdVec></MemPortIdVec>
<condition id="-1">
<or_exp><and_exp></and_exp></or_exp>
</condition>

<Node id="32" bw="8" op_0_bw="1" op_1_bw="8" op_2_bw="8">
<![CDATA[
:27 %result_11 = select i1 %tmp_3, i8 %result_10, i8 %result_9

]]></Node>
<StgValue><ssdm name="result_11"/></StgValue>
</operation>

<operation id="30" st_id="1" stage="1" lat="1">
<core>LogicGate</core>
<MemPortIdVec></MemPortIdVec>
<condition id="-1">
<or_exp><and_exp></and_exp></or_exp>
</condition>

<Node id="33" bw="8" op_0_bw="8" op_1_bw="8">
<![CDATA[
:28 %xor_ln17 = xor i8 %xor_ln16, i8 %p_read26

]]></Node>
<StgValue><ssdm name="xor_ln17"/></StgValue>
</operation>

<operation id="31" st_id="1" stage="1" lat="1">
<core>LogicGate</core>
<MemPortIdVec></MemPortIdVec>
<condition id="-1">
<or_exp><and_exp></and_exp></or_exp>
</condition>

<Node id="34" bw="8" op_0_bw="8" op_1_bw="8">
<![CDATA[
:29 %xor_ln17_1 = xor i8 %result_8, i8 %result_11

]]></Node>
<StgValue><ssdm name="xor_ln17_1"/></StgValue>
</operation>

<operation id="32" st_id="1" stage="1" lat="1">
<core>LogicGate</core>
<MemPortIdVec></MemPortIdVec>
<condition id="-1">
<or_exp><and_exp></and_exp></or_exp>
</condition>

<Node id="35" bw="8" op_0_bw="8" op_1_bw="8">
<![CDATA[
:30 %xor_ln17_2 = xor i8 %xor_ln17_1, i8 %xor_ln17

]]></Node>
<StgValue><ssdm name="xor_ln17_2"/></StgValue>
</operation>

<operation id="33" st_id="1" stage="1" lat="1">
<core>LogicGate</core>
<MemPortIdVec></MemPortIdVec>
<condition id="-1">
<or_exp><and_exp></and_exp></or_exp>
</condition>

<Node id="36" bw="8" op_0_bw="8" op_1_bw="8">
<![CDATA[
:31 %xor_ln18 = xor i8 %result_2, i8 %p_read15

]]></Node>
<StgValue><ssdm name="xor_ln18"/></StgValue>
</operation>

<operation id="34" st_id="1" stage="1" lat="1">
<core>LogicGate</core>
<MemPortIdVec></MemPortIdVec>
<condition id="-1">
<or_exp><and_exp></and_exp></or_exp>
</condition>

<Node id="37" bw="8" op_0_bw="8" op_1_bw="8">
<![CDATA[
:32 %xor_ln18_1 = xor i8 %result_11, i8 %p_read37

]]></Node>
<StgValue><ssdm name="xor_ln18_1"/></StgValue>
</operation>

<operation id="35" st_id="1" stage="1" lat="1">
<core>LogicGate</core>
<MemPortIdVec></MemPortIdVec>
<condition id="-1">
<or_exp><and_exp></and_exp></or_exp>
</condition>

<Node id="38" bw="8" op_0_bw="8" op_1_bw="8">
<![CDATA[
:33 %xor_ln18_2 = xor i8 %xor_ln18_1, i8 %p_read26

]]></Node>
<StgValue><ssdm name="xor_ln18_2"/></StgValue>
</operation>

<operation id="36" st_id="1" stage="1" lat="1">
<core>LogicGate</core>
<MemPortIdVec></MemPortIdVec>
<condition id="-1">
<or_exp><and_exp></and_exp></or_exp>
</condition>

<Node id="39" bw="8" op_0_bw="8" op_1_bw="8">
<![CDATA[
:34 %xor_ln18_3 = xor i8 %xor_ln18_2, i8 %xor_ln18

]]></Node>
<StgValue><ssdm name="xor_ln18_3"/></StgValue>
</operation>

<operation id="37" st_id="1" stage="1" lat="1">
<core>NULL</core>
<MemPortIdVec></MemPortIdVec>
<condition id="-1">
<or_exp><and_exp></and_exp></or_exp>
</condition>

<Node id="40" bw="32" op_0_bw="32" op_1_bw="8">
<![CDATA[
:35 %mrv = insertvalue i32 <undef>, i8 %xor_ln15_3

]]></Node>
<StgValue><ssdm name="mrv"/></StgValue>
</operation>

<operation id="38" st_id="1" stage="1" lat="1">
<core>NULL</core>
<MemPortIdVec></MemPortIdVec>
<condition id="-1">
<or_exp><and_exp></and_exp></or_exp>
</condition>

<Node id="41" bw="32" op_0_bw="32" op_1_bw="8">
<![CDATA[
:36 %mrv_1 = insertvalue i32 %mrv, i8 %xor_ln16_3

]]></Node>
<StgValue><ssdm name="mrv_1"/></StgValue>
</operation>

<operation id="39" st_id="1" stage="1" lat="1">
<core>NULL</core>
<MemPortIdVec></MemPortIdVec>
<condition id="-1">
<or_exp><and_exp></and_exp></or_exp>
</condition>

<Node id="42" bw="32" op_0_bw="32" op_1_bw="8">
<![CDATA[
:37 %mrv_2 = insertvalue i32 %mrv_1, i8 %xor_ln17_2

]]></Node>
<StgValue><ssdm name="mrv_2"/></StgValue>
</operation>

<operation id="40" st_id="1" stage="1" lat="1">
<core>NULL</core>
<MemPortIdVec></MemPortIdVec>
<condition id="-1">
<or_exp><and_exp></and_exp></or_exp>
</condition>

<Node id="43" bw="32" op_0_bw="32" op_1_bw="8">
<![CDATA[
:38 %mrv_3 = insertvalue i32 %mrv_2, i8 %xor_ln18_3

]]></Node>
<StgValue><ssdm name="mrv_3"/></StgValue>
</operation>

<operation id="41" st_id="1" stage="1" lat="1">
<core>NULL</core>
<MemPortIdVec></MemPortIdVec>
<condition id="-1">
<or_exp><and_exp></and_exp></or_exp>
</condition>

<Node id="44" bw="0" op_0_bw="32">
<![CDATA[
:39 %ret_ln19 = ret i32 %mrv_3

]]></Node>
<StgValue><ssdm name="ret_ln19"/></StgValue>
</operation>
</state>
</state_list>


<ports>
<port id="42" name="p_read" dir="0" iftype="0">
<core>NULL</core><StgValue><ssdm name="p_read"/></StgValue>
</port>
<port id="43" name="p_read1" dir="0" iftype="0">
<core>NULL</core><StgValue><ssdm name="p_read1"/></StgValue>
</port>
<port id="44" name="p_read2" dir="0" iftype="0">
<core>NULL</core><StgValue><ssdm name="p_read2"/></StgValue>
</port>
<port id="45" name="p_read3" dir="0" iftype="0">
<core>NULL</core><StgValue><ssdm name="p_read3"/></StgValue>
</port>
</ports>


<dataflows>
<dataflow id="47" from="_ssdm_op_Read.ap_auto.i8" to="p_read37" fromId="46" toId="2">
</dataflow>
<dataflow id="48" from="p_read3" to="p_read37" fromId="45" toId="2">
</dataflow>
<dataflow id="49" from="_ssdm_op_Read.ap_auto.i8" to="p_read26" fromId="46" toId="3">
</dataflow>
<dataflow id="50" from="p_read2" to="p_read26" fromId="44" toId="3">
</dataflow>
<dataflow id="51" from="_ssdm_op_Read.ap_auto.i8" to="p_read15" fromId="46" toId="4">
</dataflow>
<dataflow id="52" from="p_read1" to="p_read15" fromId="43" toId="4">
</dataflow>
<dataflow id="53" from="_ssdm_op_Read.ap_auto.i8" to="p_read_193" fromId="46" toId="5">
</dataflow>
<dataflow id="54" from="p_read" to="p_read_193" fromId="42" toId="5">
</dataflow>
<dataflow id="55" from="p_read_193" to="result" fromId="5" toId="6">
</dataflow>
<dataflow id="57" from="StgValue_56" to="result" fromId="56" toId="6">
</dataflow>
<dataflow id="59" from="_ssdm_op_BitSelect.i1.i8.i32" to="tmp" fromId="58" toId="7">
</dataflow>
<dataflow id="60" from="p_read_193" to="tmp" fromId="5" toId="7">
</dataflow>
<dataflow id="62" from="StgValue_61" to="tmp" fromId="61" toId="7">
</dataflow>
<dataflow id="63" from="result" to="result_1" fromId="6" toId="8">
</dataflow>
<dataflow id="65" from="StgValue_64" to="result_1" fromId="64" toId="8">
</dataflow>
<dataflow id="66" from="tmp" to="result_2" fromId="7" toId="9">
</dataflow>
<dataflow id="67" from="result_1" to="result_2" fromId="8" toId="9">
</dataflow>
<dataflow id="68" from="result" to="result_2" fromId="6" toId="9">
</dataflow>
<dataflow id="69" from="p_read15" to="result_3" fromId="4" toId="10">
</dataflow>
<dataflow id="70" from="StgValue_56" to="result_3" fromId="56" toId="10">
</dataflow>
<dataflow id="71" from="_ssdm_op_BitSelect.i1.i8.i32" to="tmp_1" fromId="58" toId="11">
</dataflow>
<dataflow id="72" from="p_read15" to="tmp_1" fromId="4" toId="11">
</dataflow>
<dataflow id="73" from="StgValue_61" to="tmp_1" fromId="61" toId="11">
</dataflow>
<dataflow id="74" from="result_3" to="result_4" fromId="10" toId="12">
</dataflow>
<dataflow id="75" from="StgValue_64" to="result_4" fromId="64" toId="12">
</dataflow>
<dataflow id="76" from="tmp_1" to="result_5" fromId="11" toId="13">
</dataflow>
<dataflow id="77" from="result_4" to="result_5" fromId="12" toId="13">
</dataflow>
<dataflow id="78" from="result_3" to="result_5" fromId="10" toId="13">
</dataflow>
<dataflow id="79" from="result_2" to="xor_ln15" fromId="9" toId="14">
</dataflow>
<dataflow id="80" from="p_read_193" to="xor_ln15" fromId="5" toId="14">
</dataflow>
<dataflow id="81" from="result_5" to="xor_ln15_1" fromId="13" toId="15">
</dataflow>
<dataflow id="82" from="p_read37" to="xor_ln15_1" fromId="2" toId="15">
</dataflow>
<dataflow id="83" from="xor_ln15_1" to="xor_ln15_2" fromId="15" toId="16">
</dataflow>
<dataflow id="84" from="p_read26" to="xor_ln15_2" fromId="3" toId="16">
</dataflow>
<dataflow id="85" from="xor_ln15_2" to="xor_ln15_3" fromId="16" toId="17">
</dataflow>
<dataflow id="86" from="xor_ln15" to="xor_ln15_3" fromId="14" toId="17">
</dataflow>
<dataflow id="87" from="p_read26" to="result_6" fromId="3" toId="18">
</dataflow>
<dataflow id="88" from="StgValue_56" to="result_6" fromId="56" toId="18">
</dataflow>
<dataflow id="89" from="_ssdm_op_BitSelect.i1.i8.i32" to="tmp_2" fromId="58" toId="19">
</dataflow>
<dataflow id="90" from="p_read26" to="tmp_2" fromId="3" toId="19">
</dataflow>
<dataflow id="91" from="StgValue_61" to="tmp_2" fromId="61" toId="19">
</dataflow>
<dataflow id="92" from="result_6" to="result_7" fromId="18" toId="20">
</dataflow>
<dataflow id="93" from="StgValue_64" to="result_7" fromId="64" toId="20">
</dataflow>
<dataflow id="94" from="tmp_2" to="result_8" fromId="19" toId="21">
</dataflow>
<dataflow id="95" from="result_7" to="result_8" fromId="20" toId="21">
</dataflow>
<dataflow id="96" from="result_6" to="result_8" fromId="18" toId="21">
</dataflow>
<dataflow id="97" from="p_read15" to="xor_ln16" fromId="4" toId="22">
</dataflow>
<dataflow id="98" from="p_read_193" to="xor_ln16" fromId="5" toId="22">
</dataflow>
<dataflow id="99" from="result_5" to="xor_ln16_1" fromId="13" toId="23">
</dataflow>
<dataflow id="100" from="xor_ln16" to="xor_ln16_1" fromId="22" toId="23">
</dataflow>
<dataflow id="101" from="result_8" to="xor_ln16_2" fromId="21" toId="24">
</dataflow>
<dataflow id="102" from="p_read37" to="xor_ln16_2" fromId="2" toId="24">
</dataflow>
<dataflow id="103" from="xor_ln16_2" to="xor_ln16_3" fromId="24" toId="25">
</dataflow>
<dataflow id="104" from="xor_ln16_1" to="xor_ln16_3" fromId="23" toId="25">
</dataflow>
<dataflow id="105" from="p_read37" to="result_9" fromId="2" toId="26">
</dataflow>
<dataflow id="106" from="StgValue_56" to="result_9" fromId="56" toId="26">
</dataflow>
<dataflow id="107" from="_ssdm_op_BitSelect.i1.i8.i32" to="tmp_3" fromId="58" toId="27">
</dataflow>
<dataflow id="108" from="p_read37" to="tmp_3" fromId="2" toId="27">
</dataflow>
<dataflow id="109" from="StgValue_61" to="tmp_3" fromId="61" toId="27">
</dataflow>
<dataflow id="110" from="result_9" to="result_10" fromId="26" toId="28">
</dataflow>
<dataflow id="111" from="StgValue_64" to="result_10" fromId="64" toId="28">
</dataflow>
<dataflow id="112" from="tmp_3" to="result_11" fromId="27" toId="29">
</dataflow>
<dataflow id="113" from="result_10" to="result_11" fromId="28" toId="29">
</dataflow>
<dataflow id="114" from="result_9" to="result_11" fromId="26" toId="29">
</dataflow>
<dataflow id="115" from="xor_ln16" to="xor_ln17" fromId="22" toId="30">
</dataflow>
<dataflow id="116" from="p_read26" to="xor_ln17" fromId="3" toId="30">
</dataflow>
<dataflow id="117" from="result_8" to="xor_ln17_1" fromId="21" toId="31">
</dataflow>
<dataflow id="118" from="result_11" to="xor_ln17_1" fromId="29" toId="31">
</dataflow>
<dataflow id="119" from="xor_ln17_1" to="xor_ln17_2" fromId="31" toId="32">
</dataflow>
<dataflow id="120" from="xor_ln17" to="xor_ln17_2" fromId="30" toId="32">
</dataflow>
<dataflow id="121" from="result_2" to="xor_ln18" fromId="9" toId="33">
</dataflow>
<dataflow id="122" from="p_read15" to="xor_ln18" fromId="4" toId="33">
</dataflow>
<dataflow id="123" from="result_11" to="xor_ln18_1" fromId="29" toId="34">
</dataflow>
<dataflow id="124" from="p_read37" to="xor_ln18_1" fromId="2" toId="34">
</dataflow>
<dataflow id="125" from="xor_ln18_1" to="xor_ln18_2" fromId="34" toId="35">
</dataflow>
<dataflow id="126" from="p_read26" to="xor_ln18_2" fromId="3" toId="35">
</dataflow>
<dataflow id="127" from="xor_ln18_2" to="xor_ln18_3" fromId="35" toId="36">
</dataflow>
<dataflow id="128" from="xor_ln18" to="xor_ln18_3" fromId="33" toId="36">
</dataflow>
<dataflow id="130" from="StgValue_129" to="mrv" fromId="129" toId="37">
</dataflow>
<dataflow id="131" from="xor_ln15_3" to="mrv" fromId="17" toId="37">
</dataflow>
<dataflow id="132" from="mrv" to="mrv_1" fromId="37" toId="38">
</dataflow>
<dataflow id="133" from="xor_ln16_3" to="mrv_1" fromId="25" toId="38">
</dataflow>
<dataflow id="134" from="mrv_1" to="mrv_2" fromId="38" toId="39">
</dataflow>
<dataflow id="135" from="xor_ln17_2" to="mrv_2" fromId="32" toId="39">
</dataflow>
<dataflow id="136" from="mrv_2" to="mrv_3" fromId="39" toId="40">
</dataflow>
<dataflow id="137" from="xor_ln18_3" to="mrv_3" fromId="36" toId="40">
</dataflow>
<dataflow id="138" from="mrv_3" to="ret_ln19" fromId="40" toId="41">
</dataflow>
<dataflow id="139" from="tmp" to="StgValue_1" fromId="7" toId="1">
</dataflow>
<dataflow id="140" from="tmp_1" to="StgValue_1" fromId="11" toId="1">
</dataflow>
<dataflow id="141" from="tmp_2" to="StgValue_1" fromId="19" toId="1">
</dataflow>
<dataflow id="142" from="tmp_3" to="StgValue_1" fromId="27" toId="1">
</dataflow>
</dataflows>


</stg>
